download_cve.py
unzip.py
fidelio/__init__.py
fidelio/__main__.py
fidelio/_version.py
fidelio/app.py
fidelio/cli.py
fidelio/methods/__init__.py
fidelio/tests/__init__.py
fidelio-0.1.dev17.dist-info/AUTHORS.rst
fidelio-0.1.dev17.dist-info/LICENSE
fidelio-0.1.dev17.dist-info/METADATA
fidelio-0.1.dev17.dist-info/WHEEL
fidelio-0.1.dev17.dist-info/entry_points.txt
fidelio-0.1.dev17.dist-info/top_level.txt
fidelio-0.1.dev17.dist-info/RECORD
