Metadata-Version: 2.1
Name: fidelio
Version: 0.1.dev17
Summary: An application for downloading and displaying Common Vulnerabilities and Exposures (CVE) from the National Vulnerabilities Database (NVD)
Home-page: https://github.com/filipStar/fidelio
Author: Filip Starcevic
Author-email: file.starcevic@gmail.com
License: UNKNOWN
Project-URL: Documentation, https://fidelio.readthedocs.io/
Project-URL: Changelog, https://fidelio.readthedocs.io/en/latest/changelog.html
Project-URL: Issue Tracker, https://github.com/filipStar/fidelio/issues
Platform: UNKNOWN
Classifier: Development Status :: 5 - Production/Stable
Classifier: Intended Audience :: Developers
Classifier: Operating System :: Unix
Classifier: Operating System :: POSIX
Classifier: Operating System :: Microsoft :: Windows
Classifier: Programming Language :: Python :: 3
Classifier: Programming Language :: Python :: 3.6
Classifier: Programming Language :: Python :: 3.7
Classifier: Programming Language :: Python :: 3.8
Classifier: Programming Language :: Python :: Implementation :: CPython
Classifier: Programming Language :: Python :: Implementation :: PyPy
Classifier: Topic :: Utilities
Requires-Python: >=2.7, !=3.0.*, !=3.1.*, !=3.2.*, !=3.3.*, !=3.4.*
Requires-Dist: click
